pico_hwd_detection/__init__.py
pico_hwd_detection/pico_hotword.py
pico_hwd_detection-1.1.2.dist-info/LICENSE
pico_hwd_detection-1.1.2.dist-info/METADATA
pico_hwd_detection-1.1.2.dist-info/WHEEL
pico_hwd_detection-1.1.2.dist-info/top_level.txt
pico_hwd_detection-1.1.2.dist-info/RECORD
