Metadata-Version: 2.1
Name: pico_hwd_detection
Version: 1.1.2
Summary: Hotword Detection with Porcupine and Python
Author: Rohit Kumar Yadav
Author-email: <rohitkuyadav2003@gmail.com>
License: MIT
Keywords: python,video,stream,video stream,camera stream,sockets
Classifier: Development Status :: 1 - Planning
Classifier: Intended Audience :: Developers
Classifier: Programming Language :: Python :: 3
Classifier: Operating System :: Unix
Classifier: Operating System :: MacOS :: MacOS X
Classifier: Operating System :: Microsoft :: Windows
Classifier: Operating System :: POSIX :: Linux
License-File: LICENSE
Requires-Dist: PyAudio
Requires-Dist: pvporcupine
Requires-Dist: colorama
